fixman/__init__.py
fixman/constants.py
fixman/utils.py
fixman/variables.py
fixman/version.py
fixman/cli/__init__.py
fixman/cli/initialize.py
fixman/cli/subcommands.py
fixman/library/__init__.py
fixman/library/commands.py
fixman/library/files.py
tests/__init__.py
tests/conftest.py
tests/test_library_commands.py
tests/test_library_files.py
tests/test_utils.py
django_fixman-1.0.0.dist-info/LICENSE.txt
django_fixman-1.0.0.dist-info/METADATA
django_fixman-1.0.0.dist-info/WHEEL
django_fixman-1.0.0.dist-info/entry_points.txt
django_fixman-1.0.0.dist-info/top_level.txt
django_fixman-1.0.0.dist-info/RECORD
