Metadata-Version: 2.1
Name: django-fixman
Version: 1.0.0
Summary: A utility for managing Django fixture data.
Home-page: https://github.com/develmaycare/django-fixman/
Author: Shawn Davis
Author-email: shawn@develmaycare.com
License: UNKNOWN
Platform: UNKNOWN
Classifier: Development Status :: 2 - Pre-Alpha
Classifier: Environment :: Console
Classifier: Intended Audience :: Developers
Classifier: License :: OSI Approved :: BSD License
Classifier: Operating System :: OS Independent
Classifier: Programming Language :: Python
Classifier: Programming Language :: Python :: 3.7
Classifier: Programming Language :: Python :: 3.8
Requires-Dist: pygments
Requires-Dist: python-commonkit
